taskprovision/__init__.py
taskprovision/api/__init__.py
taskprovision/api/auth.py
taskprovision/api/billing.py
taskprovision/api/generation.py
taskprovision/api/projects.py
taskprovision/config/__init__.py
taskprovision/config/database.py
taskprovision/config/settings.py
taskprovision/core/__init__.py
taskprovision/core/ai_analyzer.py
taskprovision/core/code_generator.py
taskprovision/core/quality_guard.py
taskprovision/core/task_manager.py
taskprovision/main.py
taskprovision/models/__init__.py
taskprovision/models/project.py
taskprovision/models/task.py
taskprovision/models/user.py
taskprovision/services/__init__.py
taskprovision/services/email_service.py
taskprovision/services/github_service.py
taskprovision/services/ollama_service.py
taskprovision/services/stripe_service.py
taskprovision/utils/__init__.py
taskprovision/utils/helpers.py
taskprovision/utils/security.py
taskprovision/utils/validators.py
taskprovision-0.1.6.dist-info/LICENSE
taskprovision-0.1.6.dist-info/METADATA
taskprovision-0.1.6.dist-info/WHEEL
taskprovision-0.1.6.dist-info/RECORD
