Metadata-Version: 2.3
Name: taskprovision
Version: 0.1.6
Summary: AI-Powered Development Automation Platform
License: Apache License
Keywords: ai,automation,development,code-generation,quality-assurance,task-management,llm,fastapi,kubernetes,devops,productivity,sales-automation
Author: TaskProvision Team
Author-email: info@softreck.dev
Maintainer: TaskProvision Team
Maintainer-email: info@softreck.dev
Requires-Python: >=3.8
Classifier: Development Status :: 4 - Beta
Classifier: Intended Audience :: Developers
Classifier: Topic :: Software Development :: Code Generators
Classifier: Topic :: Software Development :: Quality Assurance
Classifier: License :: OSI Approved :: Apache Software License
Classifier: Programming Language :: Python :: 3
Classifier: Programming Language :: Python :: 3.8
Classifier: Programming Language :: Python :: 3.9
Classifier: Programming Language :: Python :: 3.10
Classifier: Programming Language :: Python :: 3.11
Classifier: Programming Language :: Python :: 3.12
Classifier: Operating System :: OS Independent
Classifier: Environment :: Web Environment
Classifier: Framework :: FastAPI
Classifier: Topic :: Internet :: WWW/HTTP :: HTTP Servers
Classifier: Topic :: Scientific/Engineering :: Artificial Intelligence
Provides-Extra: dev
Requires-Dist: bandit (>=1.7.5) ; extra == "dev"
Requires-Dist: black (>=23.9.0) ; extra == "dev"
Requires-Dist: fakeredis (>=2.20.0) ; extra == "dev"
Requires-Dist: flake8 (>=6.1.0) ; extra == "dev"
Requires-Dist: ipdb (>=0.13.13) ; extra == "dev"
Requires-Dist: ipython (>=8.16.0) ; extra == "dev"
Requires-Dist: isort (>=5.12.0) ; extra == "dev"
Requires-Dist: memory-profiler (>=0.61.0) ; extra == "dev"
Requires-Dist: mkdocs (>=1.5.0) ; extra == "dev"
Requires-Dist: mkdocs-awesome-pages-plugin (>=2.9.0) ; extra == "dev"
Requires-Dist: mkdocs-material (>=9.4.0) ; extra == "dev"
Requires-Dist: mkdocstrings[python] (>=0.24.0) ; extra == "dev"
Requires-Dist: mypy (>=1.6.0) ; extra == "dev"
Requires-Dist: pre-commit (>=3.5.0) ; extra == "dev"
Requires-Dist: py-spy (>=0.3.14) ; extra == "dev"
Requires-Dist: pytest (>=7.4.0) ; extra == "dev"
Requires-Dist: pytest-asyncio (>=0.21.0) ; extra == "dev"
Requires-Dist: pytest-cov (>=4.1.0) ; extra == "dev"
Requires-Dist: pytest-mock (>=3.12.0) ; extra == "dev"
Requires-Dist: pytest-xdist (>=3.3.0) ; extra == "dev"
Requires-Dist: safety (>=2.3.0) ; extra == "dev"
Requires-Dist: watchdog (>=3.0.0) ; extra == "dev"
